jpl/slim/VERSION.txt
jpl/slim/__init__.py
jpl/slim/app.py
jpl/slim/cli.py
jpl/slim/testgen.py
jpl/slim/best_practices/__init__.py
jpl/slim/best_practices/base.py
jpl/slim/best_practices/docs_website.py
jpl/slim/best_practices/governance.py
jpl/slim/best_practices/practice_mapping.py
jpl/slim/best_practices/secrets_detection.py
jpl/slim/best_practices/standard.py
jpl/slim/best_practices/docs_website_impl/__init__.py
jpl/slim/best_practices/docs_website_impl/config_updater.py
jpl/slim/best_practices/docs_website_impl/content_validator.py
jpl/slim/best_practices/docs_website_impl/generator.py
jpl/slim/best_practices/docs_website_impl/helpers.py
jpl/slim/best_practices/docs_website_impl/markdown_linter.py
jpl/slim/best_practices/docs_website_impl/site_reviser.py
jpl/slim/best_practices/docs_website_impl/template_manager.py
jpl/slim/commands/__init__.py
jpl/slim/commands/apply_command.py
jpl/slim/commands/apply_deploy_command.py
jpl/slim/commands/common.py
jpl/slim/commands/deploy_command.py
jpl/slim/commands/examples.py
jpl/slim/commands/generate_tests_command.py
jpl/slim/commands/list_command.py
jpl/slim/commands/models_command.py
jpl/slim/manager/__init__.py
jpl/slim/manager/best_practices_manager.py
jpl/slim/mcp/__init__.py
jpl/slim/mcp/server.py
jpl/slim/mcp/configs/claude_code.json
jpl/slim/mcp/configs/examples/__init__.py
jpl/slim/mcp/docs/README.md
jpl/slim/mcp/docs/installation.md
jpl/slim/mcp/docs/integration.md
jpl/slim/mcp/scripts/start_mcp_server.sh
jpl/slim/mcp/scripts/start_server.py
jpl/slim/mcp/tools/README.md
jpl/slim/mcp/tools/SUMMARY.md
jpl/slim/mcp/tools/__init__.py
jpl/slim/mcp/tools/ai_tools.py
jpl/slim/mcp/tools/comprehensive_ai_tools.py
jpl/slim/mcp/tools/config.py
jpl/slim/mcp/tools/demo.py
jpl/slim/mcp/tools/enhanced_tools.py
jpl/slim/mcp/tools/examples.py
jpl/slim/mcp/tools/prompts.py
jpl/slim/mcp/tools/requirements.txt
jpl/slim/mcp/tools/resources.py
jpl/slim/mcp/tools/server.py
jpl/slim/mcp/tools/test_server.py
jpl/slim/mcp/tools/tools.py
slim_cli-2.0.0.dist-info/METADATA
slim_cli-2.0.0.dist-info/WHEEL
slim_cli-2.0.0.dist-info/entry_points.txt
slim_cli-2.0.0.dist-info/licenses/LICENSE
slim_cli-2.0.0.dist-info/RECORD
