Metadata-Version: 2.4
Name: slim-cli
Version: 2.0.0
Summary: Automation of the application of software lifecycle best practices to your GitHub repositories
Project-URL: Homepage, https://github.com/SLIM/slim-cli
Project-URL: Issues, https://github.com/SLIM/slim-cli/issues
Author-email: Rishi Verma <Rishi.Verma@jpl.nasa.gov>, Kyongsik Yun <kyongsik.yun@jpl.nasa.gov>, Sean Kelly <kelly@seankelly.biz>
License:                                  Apache License
License-File: LICENSE
Keywords: ammos,automation,development,nasa,practice,slim,software
Classifier: Development Status :: 2 - Pre-Alpha
Classifier: Environment :: Console
Classifier: Intended Audience :: Developers
Classifier: Intended Audience :: Science/Research
Classifier: License :: OSI Approved :: Apache Software License
Classifier: Natural Language :: English
Classifier: Operating System :: OS Independent
Classifier: Programming Language :: Python :: 3
Requires-Python: >=3.10
Requires-Dist: azure-identity~=1.17.1
Requires-Dist: click~=8.1.0
Requires-Dist: gitpython~=3.1.43
Requires-Dist: jinja2~=3.1.0
Requires-Dist: litellm>=1.40.0
Requires-Dist: numpy~=2.0.2
Requires-Dist: ollama~=0.3.1
Requires-Dist: openai~=1.42.0
Requires-Dist: pip>=25.1.1
Requires-Dist: python-dotenv~=1.0.1
Requires-Dist: pyyaml~=6.0.1
Requires-Dist: requests~=2.32.3
Requires-Dist: rich>=13.9.4
Requires-Dist: typer>=0.9.0
